mrql/__init__.py
mrql/codegen/__init__.py
mrql/lexer/__init__.py
mrql/parser/__init__.py
mrql-0.1.0.dist-info/licenses/LICENSE
mrql-0.1.0.dist-info/METADATA
mrql-0.1.0.dist-info/WHEEL
mrql-0.1.0.dist-info/top_level.txt
mrql-0.1.0.dist-info/RECORD
