Metadata-Version: 2.4
Name: mrql
Version: 0.1.0
Summary: MongoDB Readable Query Language
Author-email: Denis Kazakov <denis@kazakov.ru.net>
Project-URL: Homepage, https://github.com/KazakovDenis/mrql
Project-URL: Repository, https://github.com/KazakovDenis/mrql
Requires-Python: >=3.10
License-File: LICENSE
Dynamic: license-file
